mkdocs_mermaid_zoom/__init__.py
mkdocs_mermaid_zoom/plugin.py
mkdocs_mermaid_zoom/assets/mermaid-zoom.css
mkdocs_mermaid_zoom/assets/mermaid-zoom.js
mkdocs_mermaid_zoom-0.1.0.dist-info/METADATA
mkdocs_mermaid_zoom-0.1.0.dist-info/WHEEL
mkdocs_mermaid_zoom-0.1.0.dist-info/entry_points.txt
mkdocs_mermaid_zoom-0.1.0.dist-info/licenses/LICENSE
mkdocs_mermaid_zoom-0.1.0.dist-info/RECORD
